pgn2gif/__init__.py
pgn2gif/download_data.py
pgn2gif/handle_gifs.py
pgn2gif/pgn2gif.py
pgn2gif-1.0.dist-info/METADATA
pgn2gif-1.0.dist-info/RECORD
pgn2gif-1.0.dist-info/WHEEL
pgn2gif-1.0.dist-info/entry_points.txt
pgn2gif-1.0.dist-info/top_level.txt
