Metadata-Version: 2.1
Name: pgn2gif
Version: 1.0
Summary: Creates GIFs from PGNs
Home-page: https://github.com/mzfr/pgn2gif
Author: Mehtab Zafar
License: UNKNOWN
Keywords: pgn gifs
Platform: UNKNOWN
Classifier: Operating System :: POSIX :: Linux
Classifier: License :: OSI Approved :: MIT License
Classifier: Development Status :: 5 - Production/Stable
Classifier: Environment :: Console
Classifier: Intended Audience :: Developers
Classifier: Topic :: Utilities
Classifier: Programming Language :: Python :: 3
Classifier: Programming Language :: Python :: 3.4
Classifier: Programming Language :: Python :: 3.5
Requires-Dist: imageio
Requires-Dist: cairosvg
Requires-Dist: requests
Requires-Dist: python-chess
Requires-Dist: click
